<?xml version="1.0" encoding="UTF-8"?>
<navigationModel
  ns = "http://schemas.android.com?import=com.android.tools.idea.editors.navigation.model.*">
  <locations  
    class = "java.util.ArrayList">
    <statePointEntry>
      <state      
        class = "com.android.tools.idea.editors.navigation.model.ActivityState"      
        className = "com.vladimir_x.easyenglishlearn.MainActivity"/>
      <point      
        x = "500"      
        y = "1480"/>
    </statePointEntry>
    <statePointEntry>
      <state      
        class = "com.android.tools.idea.editors.navigation.model.ActivityState"      
        className = "com.vladimir_x.easyenglishlearn.word_selection.WordSelectionFragment"/>
      <point      
        x = "1768"      
        y = "100"/>
    </statePointEntry>
    <statePointEntry>
      <state      
        class = "com.android.tools.idea.editors.navigation.model.ActivityState"      
        className = "com.vladimir_x.easyenglishlearn.category_edit.CategoryEditFragment"/>
      <point      
        x = "648"      
        y = "1628"/>
    </statePointEntry>
    <statePointEntry>
      <state      
        class = "com.android.tools.idea.editors.navigation.model.ActivityState"      
        className = "com.vladimir_x.easyenglishlearn.exercises.WordConstructorFragment"/>
      <point      
        x = "700"      
        y = "1680"/>
    </statePointEntry>
    <statePointEntry>
      <state      
        class = "com.android.tools.idea.editors.navigation.model.ActivityState"      
        className = "com.vladimir_x.easyenglishlearn.exercises.WordQuizFragment"/>
      <point      
        x = "748"      
        y = "1728"/>
    </statePointEntry>
    <statePointEntry>
      <state      
        class = "com.android.tools.idea.editors.navigation.model.ActivityState"      
        className = "com.vladimir_x.easyenglishlearn.category_select.CategoryFragment"/>
      <point      
        x = "500"      
        y = "100"/>
    </statePointEntry>
  </locations>
</navigationModel>
